light_labyrinth/_tools.py
light_labyrinth/__init__.py
light_labyrinth/_bare_model.py
light_labyrinth/multioutput/_LightLabyrinth3DMultilabelClassifier.py
light_labyrinth/multioutput/_LightLabyrinth3DMultioutputRegressor.py
light_labyrinth/multioutput/_LightLabyrinth3DRandomMultioutputRegressor.py
light_labyrinth/multioutput/_LightLabyrinth3DMixedOutputPredictor.py
light_labyrinth/multioutput/_LightLabyrinth3DRandomMultilabelClassifier.py
light_labyrinth/multioutput/__init__.py
light_labyrinth/sklearn_wrappers/_SklearnRegressorWrapper.py
light_labyrinth/sklearn_wrappers/__init__.py
light_labyrinth/sklearn_wrappers/_SklearnClassifierWrapper.py
light_labyrinth/utils/_utils.py
light_labyrinth/utils/_learning_process.py
light_labyrinth/utils/__init__.py
light_labyrinth/dim2/_LightLabyrinthRandomRegressor.py
light_labyrinth/dim2/_LightLabyrinthRegressor.py
light_labyrinth/dim2/_LightLabyrinthClassifier.py
light_labyrinth/dim2/_LightLabyrinthDynamicClassifier.py
light_labyrinth/dim2/_LightLabyrinthDynamicRegressor.py
light_labyrinth/dim2/__init__.py
light_labyrinth/dim2/_LightLabyrinthRandomClassifier.py
light_labyrinth/_light_labyrinth_c/py_utils.py
light_labyrinth/_light_labyrinth_c/light_labyrinth.so
light_labyrinth/_light_labyrinth_c/_light_labyrinth_c.py
light_labyrinth/_light_labyrinth_c/__init__.py
light_labyrinth/dim3/_LightLabyrinth3DClassifier.py
light_labyrinth/dim3/_LightLabyrinth3DRandomClassifier.py
light_labyrinth/dim3/__init__.py
light_labyrinth/ensemble/_RandomMaze2DClassifier.py
light_labyrinth/ensemble/_RandomMaze3DClassifier.py
light_labyrinth/ensemble/__init__.py
light_labyrinth/ensemble/_RandomMazeRegressor.py
light_labyrinth/hyperparams/__init__.py
light_labyrinth/hyperparams/error_function/_error_function.py
light_labyrinth/hyperparams/error_function/__init__.py
light_labyrinth/hyperparams/weights_init/_weights_initialization.py
light_labyrinth/hyperparams/weights_init/__init__.py
light_labyrinth-1.0.0.dist-info/top_level.txt
light_labyrinth-1.0.0.dist-info/RECORD
light_labyrinth-1.0.0.dist-info/METADATA
light_labyrinth-1.0.0.dist-info/WHEEL
