Metadata-Version: 2.1
Name: light-labyrinth
Version: 1.0.0
Summary: Light labyrinth ML model
Home-page: https://lightlabyrinth.org
Author: Marcin Zakrzewski, Krzysztof Wieclaw
Author-email: enkar@lightlabyrinth.org, wutus@lightlabyrinth.org
Project-URL: Source Code, https://bitbucket.org/Enkar234/lightlabyrinth
Project-URL: Documentation, https://lightlabyrinth.org
Classifier: Programming Language :: Python :: 3
Classifier: License :: OSI Approved :: MIT License
Classifier: Operating System :: OS Independent
Requires-Python: >=3.8
Requires-Dist: scikit-learn
Requires-Dist: pandas
Requires-Dist: scipy
